exam_generator/__init__.py
exam_generator/exam.py
exam_generator/jinjaenv.py
exam_generator/utils.py
exam_generator/mat1/__init__.py
exam_generator/mat1/mat1exam.py
exam_generator/mat1/py2nb.py
exam_generator/mat1/w1q1/__init__.py
exam_generator/mat1/w1q1/w1q1.py
exam_generator/mat1/w1q2/__init__.py
exam_generator/mat1/w1q2/w1q2.py
exam_generator/mat1/w1verification/__init__.py
exam_generator/mat1/w1verification/verification_question.py
exam_generator/questions/__init__.py
exam_generator/questions/explicit_multiple_choice/__init__.py
exam_generator/questions/explicit_multiple_choice/explicit_multiple_choice.py
exam_generator/questions/explicit_multiple_choice/explicit_multiple_choice.tex
exam_generator/questions/multiple_choice/__init__.py
exam_generator/questions/multiple_choice/multiple_choice.py
exam_generator/questions/multiple_choice/multiple_choice.tex
exam_generator/templates/exam_base.tex
exam_generator/templates/macros.tex
exam_generator/templates/mc_question_base.tex
exam_generator/templates/multiple_choice_answers.pyt
exam_generator/templates/question_base.tex
exam_generator-0.0.8.dist-info/METADATA
exam_generator-0.0.8.dist-info/WHEEL
exam_generator-0.0.8.dist-info/top_level.txt
exam_generator-0.0.8.dist-info/RECORD
